pratidoc-1.0.0.dist-info/METADATA
pratidoc-1.0.0.dist-info/WHEEL
pratidoc-1.0.0.dist-info/entry_points.txt
pratidoc/__init__.py
pratidoc/__main__.py
pratidoc/_cli.py
pratidoc/_files.py
pratidoc/_rule/__init__.py
pratidoc/_rule/_base.py
pratidoc/_rule/_existence.py
pratidoc/_rule/rule.py
pratidoc/py.typed
pratidoc/py.typed.license
pratidoc-1.0.0.dist-info/RECORD
