Metadata-Version: 2.4
Name: pratidoc
Version: 1.0.0
Summary: Lint your repository docs - ensure the essentials are always there.
Author: open-nudge
Maintainer: open-nudge
License-Expression: Apache-2.0
Classifier: Development Status :: 2 - Pre-Alpha
Classifier: Intended Audience :: Developers
Classifier: Programming Language :: Python
Classifier: Programming Language :: Python :: 3 :: Only
Classifier: Programming Language :: Python :: 3.12
Classifier: Programming Language :: Python :: 3.13
Classifier: Programming Language :: Python :: 3.14
Classifier: Topic :: Software Development :: Libraries
Classifier: Topic :: Software Development :: Libraries :: Python Modules
Classifier: Typing :: Typed
Project-URL: Changelog, https://github.com/open-nudge/pratidoc/blob/master/CHANGELOG.md
Project-URL: Documentation, https://open-nudge.github.io/pratidoc
Project-URL: Homepage, https://open-nudge.github.io/pratidoc
Project-URL: Issues, https://github.com/open-nudge/pratidoc/issues
Project-URL: Repository, https://github.com/open-nudge/pratidoc
Requires-Python: >=3.12
Requires-Dist: lintkit[rich]>=1.0.1
Requires-Dist: loadfig>=0.1.0
